nythop/__about__.py
nythop/__init__.py
nythop/nythop.py
nythop/transpile.py
nythop-1.0.0.dist-info/METADATA
nythop-1.0.0.dist-info/WHEEL
nythop-1.0.0.dist-info/entry_points.txt
nythop-1.0.0.dist-info/licenses/LICENSE.md
nythop-1.0.0.dist-info/RECORD
