Metadata-Version: 2.3
Name: nythop
Version: 1.0.0
Summary: Nythop is an esolang that takes Python and gives it a good shake, letting you write code in reverse for a coding experience like no other!
Project-URL: Documentation, https://github.com/Luiz Eduardo Amaral/nythop#readme
Project-URL: Issues, https://github.com/Luiz Eduardo Amaral/nythop/issues
Project-URL: Source, https://github.com/Luiz Eduardo Amaral/nythop
Author-email: Luiz Eduardo Amaral <luizamaral306@gmail.com>
License: ### GNU GENERAL PUBLIC LICENSE
Keywords: esolang,esoteric,language,programming,python
Classifier: Development Status :: 4 - Beta
Classifier: License :: OSI Approved :: GNU General Public License v3 or later (GPLv3+)
Classifier: Programming Language :: Python
Classifier: Programming Language :: Python :: 3.8
Classifier: Programming Language :: Python :: 3.9
Classifier: Programming Language :: Python :: 3.10
Classifier: Programming Language :: Python :: 3.11
Classifier: Programming Language :: Python :: 3.12
Classifier: Programming Language :: Python :: Implementation :: CPython
Classifier: Programming Language :: Python :: Implementation :: PyPy
Requires-Python: >=3.8
